{
    "values": {
        "type": "AchievementDefinition",
        "id": 167,
        "subAchievements": [
            594
        ],
        "points": 10,
        "secret": false,
        "achievementType": 0,
        "rewards": [],
        "onSuccess": []
    },
    "name": {
        "fr": "Aider le Caqueleur Magmatique \u00e0 stopper les Bworks",
        "en": "Help the Magmagic Crackler stop the Bworks",
        "es": "Ayudar al crujidor magm\u00e1tico a detener a los bworks",
        "de": "Hilf dem Magma-Krachler, die Bworks aufzuhalten",
        "pt": "Ajudar o Smagador Magm\u00e1tico a parar os Bworks"
    },
    "description": {
        "fr": "",
        "en": "",
        "es": "",
        "de": "",
        "pt": ""
    },
    "descriptionFinished": {
        "fr": "",
        "en": "",
        "es": "",
        "de": "",
        "pt": ""
    }
}