{
    "values": {
        "type": "AchievementDefinition",
        "id": 20450,
        "subAchievements": [
            136
        ],
        "points": 20,
        "secret": false,
        "achievementType": 0,
        "rewards": [],
        "onSuccess": []
    },
    "name": {
        "fr": "Remporter un combat sans Powa sur le terrain",
        "en": "Win a fight without Powa on the field",
        "es": "Ganar un combate sin ning\u00fan powa en el terreno",
        "de": "Gewinn einen Kampf ohne Powa auf dem Spielfeld",
        "pt": "Vencer um combate sem Powa em campo"
    },
    "description": {
        "fr": "",
        "en": "",
        "es": "",
        "de": "",
        "pt": ""
    },
    "descriptionFinished": {
        "fr": "",
        "en": "",
        "es": "",
        "de": "",
        "pt": ""
    }
}