{
    "animatedCharacterDataReference": {
        "assetGuid": "f0e9aa562da6c474e8aa4d56765ba1cc"
    },
    "animatedCharacterUIPreviewReference": {
        "assetGuid": ""
    },
    "animatedCharacterUIPreviewScale": 1,
    "animatedIllustrationReference": {
        "assetGuid": ""
    },
    "illustrationReference": {
        "assetGuid": "9c4174f9614d4ad46a15b21739181e6a"
    },
    "slotIllustrationReference": {
        "assetGuid": ""
    },
    "npcTalkFightVictoryAssetReference": {
        "assetGuid": ""
    },
    "npcTalkFightDefeatAssetReference": {
        "assetGuid": ""
    },
    "npcTalkQuestTalkAssetReference": {
        "assetGuid": ""
    },
    "npcTalkQuestSuccessAssetReference": {
        "assetGuid": ""
    },
    "questSmallIllustrationAssetReference": {
        "assetGuid": ""
    },
    "voiceLine": {
        "m_eventGuid": "",
        "m_parameterIds": [],
        "m_parameterValues": []
    },
    "values": {
        "type": "CharacterSkinDefinition",
        "id": 4225,
        "rarity": 0,
        "merchantCosts": [],
        "premiumItem": false,
        "precomputedData": {
            "type": "PrecomputedData",
            "dynamicValueReferences": [],
            "externalDynamicValueReferences": [],
            "hasEffects": false,
            "keywordReferences": []
        },
        "characterSkinType": 6,
        "gender": 1,
        "defaultEmotes": [],
        "faction": null
    },
    "name": {
        "fr": "La Montagne",
        "en": "The Mountain",
        "es": "Monta\u00f1a",
        "de": "Der Berg",
        "pt": "A Montanha"
    }
}