{
    "animatedCharacterDataReference": {
        "assetGuid": "784cce2d940064d4c8f48bf38aa89161"
    },
    "animatedCharacterUIPreviewReference": {
        "assetGuid": "8b6cbacd24668d04a950c80710c5042a"
    },
    "animatedCharacterUIPreviewScale": 1,
    "animatedIllustrationReference": {
        "assetGuid": "b07e44dabe9576a479149e64e9d105cb"
    },
    "illustrationReference": {
        "assetGuid": "8bef2fc1735021e44a58ca1fc67afa1e"
    },
    "slotIllustrationReference": {
        "assetGuid": "4063e6a315e07d942baff254121e214f"
    },
    "npcTalkFightVictoryAssetReference": {
        "assetGuid": ""
    },
    "npcTalkFightDefeatAssetReference": {
        "assetGuid": ""
    },
    "npcTalkQuestTalkAssetReference": {
        "assetGuid": ""
    },
    "npcTalkQuestSuccessAssetReference": {
        "assetGuid": ""
    },
    "questSmallIllustrationAssetReference": {
        "assetGuid": ""
    },
    "voiceLine": {
        "m_eventGuid": "5f2b0bb44e6a4962b722bb6d13a16667",
        "m_parameterIds": [],
        "m_parameterValues": []
    },
    "values": {
        "type": "CharacterSkinDefinition",
        "id": 5769,
        "rarity": 0,
        "merchantCosts": [],
        "premiumItem": false,
        "precomputedData": {
            "type": "PrecomputedData",
            "dynamicValueReferences": [],
            "externalDynamicValueReferences": [],
            "hasEffects": false,
            "keywordReferences": []
        },
        "characterSkinType": 7,
        "gender": 1,
        "defaultEmotes": [
            828,
            870,
            988
        ],
        "faction": null
    },
    "name": {
        "fr": "Gemme D\u00e9phasante",
        "en": "Dephasing Gem",
        "es": "Gema Desfasadora",
        "de": "Phasenstein",
        "pt": "Gema Defasante"
    }
}