{
    "animatedCharacterDataReference": {
        "assetGuid": "41c4d6e4bf539d7489b1e5732542615a"
    },
    "animatedCharacterUIPreviewReference": {
        "assetGuid": ""
    },
    "animatedCharacterUIPreviewScale": 1,
    "animatedIllustrationReference": {
        "assetGuid": ""
    },
    "illustrationReference": {
        "assetGuid": "bdfa7431b60d9644f93a3f97064d7ccf"
    },
    "slotIllustrationReference": {
        "assetGuid": ""
    },
    "npcTalkFightVictoryAssetReference": {
        "assetGuid": ""
    },
    "npcTalkFightDefeatAssetReference": {
        "assetGuid": ""
    },
    "npcTalkQuestTalkAssetReference": {
        "assetGuid": ""
    },
    "npcTalkQuestSuccessAssetReference": {
        "assetGuid": ""
    },
    "questSmallIllustrationAssetReference": {
        "assetGuid": ""
    },
    "voiceLine": {
        "m_eventGuid": "",
        "m_parameterIds": [],
        "m_parameterValues": []
    },
    "values": {
        "type": "CharacterSkinDefinition",
        "id": 5989,
        "rarity": 0,
        "merchantCosts": [],
        "premiumItem": false,
        "precomputedData": {
            "type": "PrecomputedData",
            "dynamicValueReferences": [],
            "externalDynamicValueReferences": [],
            "hasEffects": false,
            "keywordReferences": []
        },
        "characterSkinType": 6,
        "gender": 1,
        "defaultEmotes": [],
        "faction": null
    },
    "name": {
        "fr": "Moogr",
        "en": "Moogrr",
        "es": "Muuugresa",
        "de": "Moogar",
        "pt": "Mugrr"
    }
}