{
    "animatedCharacterDataReference": {
        "assetGuid": "931af433cd269614397ac0151866dcee"
    },
    "animatedCharacterUIPreviewReference": {
        "assetGuid": ""
    },
    "animatedCharacterUIPreviewScale": 1,
    "animatedIllustrationReference": {
        "assetGuid": ""
    },
    "illustrationReference": {
        "assetGuid": ""
    },
    "slotIllustrationReference": {
        "assetGuid": ""
    },
    "npcTalkFightVictoryAssetReference": {
        "assetGuid": ""
    },
    "npcTalkFightDefeatAssetReference": {
        "assetGuid": ""
    },
    "npcTalkQuestTalkAssetReference": {
        "assetGuid": ""
    },
    "npcTalkQuestSuccessAssetReference": {
        "assetGuid": ""
    },
    "questSmallIllustrationAssetReference": {
        "assetGuid": ""
    },
    "voiceLine": {
        "m_eventGuid": "c16da9e126bf4a5b9f286b104b85def6",
        "m_parameterIds": [],
        "m_parameterValues": []
    },
    "values": {
        "type": "CharacterSkinDefinition",
        "id": 7101,
        "rarity": 0,
        "merchantCosts": [],
        "premiumItem": false,
        "precomputedData": {
            "type": "PrecomputedData",
            "dynamicValueReferences": [],
            "externalDynamicValueReferences": [],
            "hasEffects": false,
            "keywordReferences": []
        },
        "characterSkinType": 0,
        "gender": 2,
        "defaultEmotes": [],
        "faction": null
    },
    "name": {
        "fr": "Ombre Glac\u00e9e",
        "en": "",
        "es": "",
        "de": "",
        "pt": "Sombra Congelada"
    }
}