{
    "animatedCharacterDataReference": {
        "assetGuid": "5593b1cdef3b91d4d9c5155894c838ee"
    },
    "animatedCharacterUIPreviewReference": {
        "assetGuid": ""
    },
    "animatedCharacterUIPreviewScale": 1,
    "animatedIllustrationReference": {
        "assetGuid": ""
    },
    "illustrationReference": {
        "assetGuid": "2e390357759ee534fa233d12eec3471d"
    },
    "slotIllustrationReference": {
        "assetGuid": ""
    },
    "npcTalkFightVictoryAssetReference": {
        "assetGuid": ""
    },
    "npcTalkFightDefeatAssetReference": {
        "assetGuid": ""
    },
    "npcTalkQuestTalkAssetReference": {
        "assetGuid": ""
    },
    "npcTalkQuestSuccessAssetReference": {
        "assetGuid": ""
    },
    "questSmallIllustrationAssetReference": {
        "assetGuid": ""
    },
    "voiceLine": {
        "m_eventGuid": "",
        "m_parameterIds": [],
        "m_parameterValues": []
    },
    "values": {
        "type": "CharacterSkinDefinition",
        "id": 8596,
        "rarity": 0,
        "merchantCosts": [],
        "premiumItem": false,
        "precomputedData": {
            "type": "PrecomputedData",
            "dynamicValueReferences": [],
            "externalDynamicValueReferences": [],
            "hasEffects": false,
            "keywordReferences": []
        },
        "characterSkinType": 3,
        "gender": 1,
        "defaultEmotes": [],
        "faction": null
    },
    "name": {
        "fr": "Meurtri\u00e8re",
        "en": "Arrow Slit",
        "es": "Mort\u00edfera",
        "de": "M\u00f6rderin",
        "pt": "Seteira"
    }
}