{
    "animatedCharacterDataReference": {
        "assetGuid": "509d1b530d7c82c48bcbd7c4d396cef8"
    },
    "animatedCharacterUIPreviewReference": {
        "assetGuid": "b470ec26524711947b744c90903e3cb7"
    },
    "animatedCharacterUIPreviewScale": 1,
    "animatedIllustrationReference": {
        "assetGuid": ""
    },
    "illustrationReference": {
        "assetGuid": "40548ecb58de3db44abda7fd203a0079"
    },
    "slotIllustrationReference": {
        "assetGuid": "9d6d826ac3474f440816f4b6faa409e9"
    },
    "npcTalkFightVictoryAssetReference": {
        "assetGuid": ""
    },
    "npcTalkFightDefeatAssetReference": {
        "assetGuid": ""
    },
    "npcTalkQuestTalkAssetReference": {
        "assetGuid": ""
    },
    "npcTalkQuestSuccessAssetReference": {
        "assetGuid": ""
    },
    "questSmallIllustrationAssetReference": {
        "assetGuid": ""
    },
    "voiceLine": {
        "m_eventGuid": "",
        "m_parameterIds": [],
        "m_parameterValues": []
    },
    "values": {
        "type": "CharacterSkinDefinition",
        "id": 9635,
        "rarity": 0,
        "merchantCosts": [],
        "premiumItem": false,
        "precomputedData": {
            "type": "PrecomputedData",
            "dynamicValueReferences": [],
            "externalDynamicValueReferences": [],
            "hasEffects": false,
            "keywordReferences": []
        },
        "characterSkinType": 4,
        "gender": 1,
        "defaultEmotes": [],
        "faction": null
    },
    "name": {
        "fr": "Yaki",
        "en": "Yaki",
        "es": "Yaki",
        "de": "Yaki",
        "pt": "Yaki"
    }
}