{
    "values": {
        "type": "WeaponDefinition",
        "id": 143,
        "areaDefinition": {
            "type": "PointAreaDefinition"
        },
        "characterSpecificSkins": {
            "type": "CharacterSpecificSkins",
            "defaultSkinId": 7460,
            "skinIds": [
                7063,
                9538,
                4316,
                7843,
                9810,
                7460
            ]
        },
        "precomputedData": {
            "type": "PrecomputedData",
            "dynamicValueReferences": [],
            "externalDynamicValueReferences": [],
            "hasEffects": true,
            "keywordReferences": [
                {
                    "type": 4,
                    "id": 898
                },
                {
                    "type": 25,
                    "id": 960
                }
            ]
        },
        "families": [
            1
        ],
        "baseProperties": [],
        "life": {
            "type": "ConstIntegerValue",
            "referenceId": "",
            "value": 396
        },
        "movementPoints": {
            "type": "ConstIntegerValue",
            "referenceId": "",
            "value": 3
        },
        "actionValue": {
            "type": "ConstIntegerValue",
            "referenceId": "",
            "value": 26
        },
        "riposte": null,
        "actionCriticalChance": {
            "type": "ConstIntegerValue",
            "referenceId": "",
            "value": 50
        },
        "actionCriticalBonus": null,
        "customActionTarget": null,
        "actionType": 1,
        "actionRange": null,
        "lifeScale": {
            "type": "ReferenceScalingFactor",
            "reference": 13
        },
        "attackScale": {
            "type": "ReferenceScalingFactor",
            "reference": 10
        },
        "merchantCosts": [],
        "premiumItem": false,
        "unlockableSkillIds": [
            132,
            760625,
            761279,
            761496
        ],
        "difficultyHint": 3,
        "defaultSkinIdMale": 7460,
        "defaultSkinIdFemale": 7063,
        "god": 1,
        "playerActionPoints": {
            "type": "ConstIntegerValue",
            "referenceId": "",
            "value": 6
        },
        "unlockableSpells": [
            914,
            424,
            590,
            112161
        ],
        "presetSpellIndexForTutorialCompanionElementReference": 1,
        "presetSpellIds": [
            319,
            946,
            202995,
            234,
            856,
            202467,
            344,
            142,
            239
        ]
    },
    "name": {
        "fr": "Lamarguedon Spectral",
        "en": "Spectral Armabladegeddon",
        "es": "Hojarmaged\u00f3n Espectral",
        "de": "Spectrageddon",
        "pt": "L\u00e2minagedom Espectral"
    },
    "description": {
        "fr": "{%FightStarted} Ajoute le sort {Spell:960} \u00e0 votre main.",
        "en": "{%FightStarted} Adds the {Spell:960} spell to your hand.",
        "es": "{%FightStarted} A\u00f1ade el hechizo {Spell:960} a tu mano.",
        "de": "{%FightStarted} F\u00fcgt deiner Hand den Zauber {Spell:960} hinzu.",
        "pt": "{%FightStarted} Adiciona o feiti\u00e7o {Spell:960} \u00e0 sua m\u00e3o."
    },
    "gameplayDescription": {
        "fr": "{Summoning:898}\\_: Une fois sur le terrain, cette cr\u00e9ature infligera des d\u00e9g\u00e2ts bas\u00e9s sur votre {%at}\\_!\n\\---\n<color=#7FD5E4>{%AT}</color>\\_: Votre force brute\\_! Plus vous l'am\u00e9liorerez, plus vous taperez fort\\_!\n\\---\n<color=#7FD5E4>SORTS</color>\\_: Votre cr\u00e9ature n'est pas vraiment vivante... Aucune raison de ne pas la sacrifier contre quelques d\u00e9g\u00e2ts suppl\u00e9mentaires\\_!",
        "en": "{Summoning:898}: Once on the field, this creature will do damage based on your {%at}!\n\\---\n<color=#7FD5E4>{%AT}</color>: Your raw strength! The more you improve it, the harder you'll hit!\n\\---\n<color=#7FD5E4>SPELLS</color>: Your creature isn't really alive\u2026 Why not sacrifice it to do extra damage?!",
        "es": "{Summoning:898}: Una vez en el terreno, esta criatura infligir\u00e1 da\u00f1os basados en tu {%at}.\n\\---\n<color=#7FD5E4>{%AT}</color>: \u00a1Tu fuerza bruta! Cuanto m\u00e1s lo mejores, \u00a1m\u00e1s fuerte golpear\u00e1s!\n\\---\n<color=#7FD5E4>HECHIZOS</color>: Tu criatura no est\u00e1 viva de verdad\u2026 \u00a1No hay raz\u00f3n para no sacrificarla a cambio de algunos da\u00f1os adicionales!",
        "de": "{Summoning:898}: Ist sie erst einmal auf dem Spielfeld, verursacht diese Kreatur Schaden entsprechend deines {%at}!\n\\---\n<color=#7FD5E4>{%AT}</color>: Deine rohe Kraft! Je mehr du sie verbesserst, desto st\u00e4rker schl\u00e4gst du zu!\n\\---\n<color=#7FD5E4>ZAUBER</color>: Deine Kreatur lebt nicht wirklich\\_\u2026 Es gibt also keinen Grund, sie nicht f\u00fcr irgendwelchen zus\u00e4tzlichen Schaden zu opfern!",
        "pt": "{Summoning:898}: No campo de batalha, esta criatura causa dano com base no seu {%at}!\n\\---\n<color=#7FD5E4>{%AT}</color>: Sua for\u00e7a bruta! Quanto mais voc\u00ea aprimorar, mais fortes ser\u00e3o os seus golpes!\n\\---\n<color=#7FD5E4>FEITI\u00c7OS</color>: Sua criatura n\u00e3o est\u00e1 viva de verdade... Por que n\u00e3o sacrific\u00e1-la para causar dano adicional?!"
    },
    "simpleName": {
        "fr": "{%OnboardingSimpleNameIop}",
        "en": "{%OnboardingSimpleNameIop}",
        "es": "{%OnboardingSimpleNameIop}",
        "de": "{%OnboardingSimpleNameIop}",
        "pt": "{%OnboardingSimpleNameIop}"
    },
    "simpleDescription": {
        "fr": "{%OnboardingSimpleDescriptionIop}",
        "en": "{%OnboardingSimpleDescriptionIop}",
        "es": "{%OnboardingSimpleDescriptionIop}",
        "de": "{%OnboardingSimpleDescriptionIop}",
        "pt": "{%OnboardingSimpleDescriptionIop}"
    }
}