{
    "values": {
        "type": "WeaponDefinition",
        "id": 846,
        "areaDefinition": {
            "type": "PointAreaDefinition"
        },
        "characterSpecificSkins": {
            "type": "CharacterSpecificSkins",
            "defaultSkinId": 2854,
            "skinIds": [
                1778,
                1222,
                1841,
                1755,
                4992,
                2854
            ]
        },
        "precomputedData": {
            "type": "PrecomputedData",
            "dynamicValueReferences": [
                {
                    "type": "SumValue",
                    "referenceId": "v",
                    "valuesToSum": [
                        {
                            "type": "ConstIntegerValue",
                            "referenceId": null,
                            "value": 50
                        },
                        {
                            "type": "ConditionalValue",
                            "referenceId": "",
                            "condition": {
                                "type": "HolderHasSkillCondition",
                                "skill": 136796
                            },
                            "ifTrue": {
                                "type": "ConstIntegerValue",
                                "referenceId": "p",
                                "value": 50
                            },
                            "ifFalse": {
                                "type": "ConstIntegerValue",
                                "referenceId": "",
                                "value": 0
                            }
                        }
                    ]
                },
                {
                    "type": "ConstIntegerValue",
                    "referenceId": "p",
                    "value": 50
                }
            ],
            "externalDynamicValueReferences": [],
            "hasEffects": true,
            "keywordReferences": []
        },
        "families": [
            2
        ],
        "baseProperties": [],
        "life": {
            "type": "ConstIntegerValue",
            "referenceId": "",
            "value": 385
        },
        "movementPoints": {
            "type": "ConstIntegerValue",
            "referenceId": "",
            "value": 3
        },
        "actionValue": {
            "type": "ConstIntegerValue",
            "referenceId": "",
            "value": 20
        },
        "riposte": null,
        "actionCriticalChance": {
            "type": "ConstIntegerValue",
            "referenceId": "",
            "value": 50
        },
        "actionCriticalBonus": null,
        "customActionTarget": null,
        "actionType": 1,
        "actionRange": null,
        "lifeScale": {
            "type": "ReferenceScalingFactor",
            "reference": 13
        },
        "attackScale": {
            "type": "ReferenceScalingFactor",
            "reference": 10
        },
        "merchantCosts": [],
        "premiumItem": false,
        "unlockableSkillIds": [
            725444,
            725672,
            735311,
            735398
        ],
        "difficultyHint": 1,
        "defaultSkinIdMale": 1778,
        "defaultSkinIdFemale": 2854,
        "god": 2,
        "playerActionPoints": {
            "type": "ConstIntegerValue",
            "referenceId": "",
            "value": 6
        },
        "unlockableSpells": [
            125,
            208505,
            904,
            746
        ],
        "presetSpellIndexForTutorialCompanionElementReference": 2,
        "presetSpellIds": [
            207193,
            207969,
            621,
            866,
            617,
            99,
            137708,
            208183,
            335
        ]
    },
    "name": {
        "fr": "Arc Piven",
        "en": "Piven Bow",
        "es": "Arco Piven",
        "de": "Tannenbogen",
        "pt": "Arco Piven"
    },
    "description": {
        "fr": "Lorsque votre h\u00e9ros lib\u00e8re une {%AURA_SIGHT,plural:one}\\_: Inflige {value:v,percent} de son {%AT} \u00e0 la cible.",
        "en": "When your hero releases a {%AURA_SIGHT,plural:one}: Inflicts {value:v,percent} of their {%AT} on the target.",
        "es": "Cuando tu h\u00e9roe libera un {%AURA_SIGHT,plural:one}: Inflige un {value:v,percent} de su {%AT} al objetivo.",
        "de": "Wenn dein Held eine {%AURA_SIGHT,plural:one} ausl\u00f6st: Verursacht beim Ziel {value:v,percent} seines {%AT} als Schaden.",
        "pt": "Quando seu her\u00f3i libera uma {%AURA_SIGHT,plural:one}: Inflige {value:v,percent} de seu {%AT} ao alvo."
    },
    "gameplayDescription": {
        "fr": "<color=#7FD5E4>AURA MIRE</color>\\_: Cette fl\u00e8che magique gravite autour de vous pour infliger des d\u00e9g\u00e2ts en plus quand vous jouez un sort.\n\\---\n<color=#7FD5E4>{%AT}</color>\\_: Votre force brute\\_! Plus vous l'am\u00e9liorerez, plus vous taperez fort\\_!",
        "en": "<color=#7FD5E4>DART AURA</color>: This magical dart gravitates around you to do extra damage when you play a spell.\n\\---\n<color=#7FD5E4>{%AT}</color>: Your raw strength! The more you improve it, the harder you'll hit!",
        "es": "<color=#7FD5E4>AURA MIRA</color>: Esta flecha m\u00e1gica gravita a tu alrededor e inflige da\u00f1os adicionales cuando lanzas un hechizo.\n\\---\n<color=#7FD5E4>{%AT}</color>: \u00a1Tu fuerza bruta! Cuanto m\u00e1s lo mejores, \u00a1m\u00e1s fuerte golpear\u00e1s!",
        "de": "<color=#7FD5E4>PHANTOMAURA</color>: Dieser magische Pfeil umkreist dich, damit du mehr Schaden verursachen kannst, wenn du einen Zauber ausspielst.\n\\---\n<color=#7FD5E4>{%AT}</color>: Deine rohe Kraft! Je mehr du sie verbesserst, desto st\u00e4rker schl\u00e4gst du zu!",
        "pt": "<color=#7FD5E4>AURA MIRA</color>: Esta flecha m\u00e1gica gravita ao seu redor para causar dano adicional quando voc\u00ea lan\u00e7ar um feiti\u00e7o.\n\\---\n<color=#7FD5E4>{%AT}</color>: Sua for\u00e7a bruta! Quanto mais voc\u00ea aprimorar, mais fortes ser\u00e3o os seus golpes!"
    },
    "simpleName": {
        "fr": "{%OnboardingSimpleNameCra}",
        "en": "{%OnboardingSimpleNameCra}",
        "es": "{%OnboardingSimpleNameCra}",
        "de": "{%OnboardingSimpleNameCra}",
        "pt": "{%OnboardingSimpleNameCra}"
    },
    "simpleDescription": {
        "fr": "{%OnboardingSimpleDescriptionCra}",
        "en": "{%OnboardingSimpleDescriptionCra}",
        "es": "{%OnboardingSimpleDescriptionCra}",
        "de": "{%OnboardingSimpleDescriptionCra}",
        "pt": "{%OnboardingSimpleDescriptionCra}"
    }
}