{
    "values": {
        "type": "SkillDefinition",
        "id": 150222,
        "skillUsageType": 1,
        "hideDescriptionInTooltip": false,
        "passiveModifiers": [],
        "nonFightSkillEffects": [],
        "precomputedData": {
            "type": "PrecomputedData",
            "dynamicValueReferences": [],
            "externalDynamicValueReferences": [],
            "hasEffects": false,
            "keywordReferences": [
                "EPHEMERAL",
                {
                    "type": 25,
                    "id": 552
                }
            ]
        }
    },
    "name": {
        "fr": "{%NEW_SKILL}",
        "en": "{%NEW_SKILL}",
        "es": "{%NEW_SKILL}",
        "de": "{%NEW_SKILL}",
        "pt": "{%NEW_SKILL}"
    },
    "description": {
        "fr": "{%ATTACK} Ajoute le sort {Spell:552} \u00e0 votre main.",
        "en": "{%ATTACK} Adds the {Spell:552} spell to your hand.",
        "es": "{%ATTACK} A\u00f1ade el hechizo {Spell:552} a tu mano.",
        "de": "{%ATTACK} F\u00fcgt deiner Hand den Zauber {Spell:552} hinzu.",
        "pt": "{%ATTACK} Adiciona o feiti\u00e7o {Spell:552} \u00e0 sua m\u00e3o."
    }
}