{
    "values": {
        "type": "SummoningDefinition",
        "id": 890,
        "areaDefinition": {
            "type": "PointAreaDefinition"
        },
        "characterSpecificSkins": {
            "type": "CharacterSpecificSkins",
            "defaultSkinId": 3115,
            "skinIds": [
                3115
            ]
        },
        "precomputedData": {
            "type": "PrecomputedData",
            "dynamicValueReferences": [],
            "externalDynamicValueReferences": [],
            "hasEffects": true,
            "keywordReferences": [
                "OBJECTMECHANISM",
                {
                    "type": 7,
                    "id": 1942
                },
                {
                    "type": 19,
                    "id": 311
                }
            ]
        },
        "families": [
            40
        ],
        "baseProperties": [],
        "life": {
            "type": "ConstIntegerValue",
            "referenceId": "",
            "value": 82
        },
        "movementPoints": {
            "type": "ConstIntegerValue",
            "referenceId": "",
            "value": 3
        },
        "actionValue": {
            "type": "ConstIntegerValue",
            "referenceId": "",
            "value": 17
        },
        "riposte": null,
        "actionCriticalChance": {
            "type": "ConstIntegerValue",
            "referenceId": "",
            "value": 150
        },
        "actionCriticalBonus": null,
        "customActionTarget": null,
        "actionType": 1,
        "actionRange": null,
        "lifeScale": {
            "type": "ReferenceScalingFactor",
            "reference": 16
        },
        "attackScale": {
            "type": "ReferenceScalingFactor",
            "reference": 7
        },
        "spells": [],
        "grade": 1,
        "growInto": null
    },
    "name": {
        "fr": "{0, plural, one[Ch\u00e2treuse Pikaross] other[Ch\u00e2treuses Pikaross]}",
        "en": "{0, plural, one[Pikaross Neutress] other[Pikaross Neutresses]}",
        "es": "{0, plural, one[Parka Pikaross] other[Parkas Pikaross]}",
        "de": "{0, plural, one[Pikaross-Lik\u00f6rkatze] other[Pikaross-Lik\u00f6rkatzen]}",
        "pt": "{0, plural, one[Chafadora Pikaross] other[Chafadoras Pikaross]}"
    },
    "description": {
        "fr": "<rem>{NamedEffect:311}</rem>\n\\---\n{%FightTurnStarted} Traverse une ligne et inflige son {%at} aux adversaires travers\u00e9s.",
        "en": "<rem>{NamedEffect:311}</rem>\n\\---\n{%FightTurnStarted} Goes down a line and inflicts {%at} on opponents gone through.",
        "es": "<rem>{NamedEffect:311}</rem>\n\\---\n{%FightTurnStarted} Atraviesa una l\u00ednea e inflige su {%at} a los adversarios atravesados.",
        "de": "<rem>{NamedEffect:311}</rem>\n\\---\n{%FightTurnStarted} \u00dcberquert eine Reihe und f\u00fcgt den \u00fcberquerten Gegnern ihren {%at} als Schaden zu.",
        "pt": "<rem>{NamedEffect:311}</rem>\n\\---\n{%FightTurnStarted}Atravessa uma linha e inflige seu {%at} aos advers\u00e1rios que atravessa."
    },
    "championName": {
        "fr": "Castresse la Frigide",
        "en": "Castratette the Frigid",
        "es": "Castrata la Fr\u00edgida",
        "de": "Frigide Kastriererin",
        "pt": "Castrete, a Fr\u00edgida"
    }
}