{
    "values": {
        "type": "SummoningDefinition",
        "id": 909,
        "areaDefinition": {
            "type": "PointAreaDefinition"
        },
        "characterSpecificSkins": {
            "type": "CharacterSpecificSkins",
            "defaultSkinId": 2061,
            "skinIds": [
                2061
            ]
        },
        "precomputedData": {
            "type": "PrecomputedData",
            "dynamicValueReferences": [
                {
                    "type": "BuffedScalingDynamicValue",
                    "referenceId": "ar",
                    "baseValue": {
                        "type": "ConstIntegerValue",
                        "referenceId": null,
                        "value": 10
                    },
                    "factor": {
                        "type": "ReferenceScalingFactor",
                        "reference": 16
                    },
                    "buffs": [
                        48
                    ],
                    "skillBuffs": [],
                    "from": {
                        "type": "EffectHolderSelector"
                    },
                    "addInsteadOfMultiply": false
                }
            ],
            "externalDynamicValueReferences": [],
            "hasEffects": true,
            "keywordReferences": []
        },
        "families": [
            75,
            100
        ],
        "baseProperties": [],
        "life": {
            "type": "ConstIntegerValue",
            "referenceId": "",
            "value": 130
        },
        "movementPoints": {
            "type": "ConstIntegerValue",
            "referenceId": "",
            "value": 2
        },
        "actionValue": {
            "type": "ConstIntegerValue",
            "referenceId": "",
            "value": 10
        },
        "riposte": null,
        "actionCriticalChance": {
            "type": "ConstIntegerValue",
            "referenceId": "",
            "value": 250
        },
        "actionCriticalBonus": null,
        "customActionTarget": null,
        "actionType": 1,
        "actionRange": null,
        "lifeScale": {
            "type": "ReferenceScalingFactor",
            "reference": 16
        },
        "attackScale": {
            "type": "ReferenceScalingFactor",
            "reference": 7
        },
        "spells": [],
        "grade": 1,
        "growInto": null
    },
    "name": {
        "fr": "B-800 Mk.3",
        "en": "B-800 Mk.3",
        "es": "B-800 Mk.3",
        "de": "B-800 Mk.3",
        "pt": "B-800 Mk.3"
    },
    "description": {
        "fr": "{%Attack} Inflige son {%AR,plural:other} en plus de son {%AT}.\n\\---\nLorsqu'un alli\u00e9 subit une {%AT}\\_: {ARvalue:ar,+}.",
        "en": "{%Attack} Inflicts its {%AR,plural:other} in addition to its {%AT}.\n\\---\nWhen an ally endures an {%AT}: {ARvalue:ar,+}.",
        "es": "{%Attack} Inflige su {%AR,plural:other} y su {%AT}.\n\\---\nCuando un aliado recibe un {%AT}: {ARvalue:ar,+}.",
        "de": "{%Attack} Verursacht seine {%AR,plural:other} zus\u00e4tzlich zu seinem {%AT} als Schaden.\n\\---\nWenn ein Verb\u00fcndeter einen {%AT} erleidet: {ARvalue:ar,+}.",
        "pt": "{%Attack} Inflige {%AR,plural:other} al\u00e9m de seu {%AT}.\n\\---\nQuando um aliado sofre um {%AT}: {ARvalue:ar,+}."
    },
    "championName": {
        "fr": "B-800 Mk.3",
        "en": "B-800 Mk.3",
        "es": "B-800 Mk.3",
        "de": "B-800 Mk.3",
        "pt": "B-800 Mk.3"
    }
}