{
    "values": {
        "type": "SpellDefinition",
        "id": 128061,
        "merchantCosts": [],
        "premiumItem": false,
        "rarity": 0,
        "unlockableSkillIds": [
            122030,
            131523
        ],
        "upgradeRuleId": null,
        "canCrit": false,
        "isEphemeral": false,
        "tags": [],
        "details": {
            "type": "SpellDetails",
            "equipableByPlayers": false,
            "element": 1,
            "specificToWeapon": 995,
            "families": [
                11
            ],
            "heroSkillPointsCost": null,
            "bannedInPvp": false
        },
        "gaugeToModifyOnSpellPlay": [
            {
                "type": "GaugeValue",
                "element": 11,
                "value": {
                    "type": "ConstIntegerValue",
                    "referenceId": "",
                    "value": 2
                }
            }
        ],
        "costs": [
            {
                "type": "ActionPointsCost",
                "value": {
                    "type": "ConstIntegerValue",
                    "referenceId": "",
                    "value": 7
                }
            }
        ],
        "castCondition": null,
        "castTarget": {
            "type": "OneCastTargetDefinition",
            "selector": {
                "type": "AllCharactersSelector"
            }
        },
        "spellEffectData": [],
        "precomputedData": {
            "type": "PrecomputedData",
            "dynamicValueReferences": [
                {
                    "type": "ConstIntegerValue",
                    "referenceId": "n",
                    "value": 5
                },
                {
                    "type": "BuffedScalingDynamicValue",
                    "referenceId": "dmg",
                    "baseValue": {
                        "type": "ConstIntegerValue",
                        "referenceId": "",
                        "value": 32
                    },
                    "factor": {
                        "type": "ReferenceScalingFactor",
                        "reference": 12
                    },
                    "buffs": [
                        51,
                        25
                    ],
                    "skillBuffs": [],
                    "from": {
                        "type": "CasterSelector"
                    },
                    "addInsteadOfMultiply": false
                }
            ],
            "externalDynamicValueReferences": [],
            "hasEffects": true,
            "keywordReferences": [
                "LIFESTEAL"
            ]
        }
    },
    "name": {
        "fr": "Grignoter",
        "en": "",
        "es": "",
        "de": "",
        "pt": ""
    },
    "description": {
        "fr": "Inflige {magicalDamage:dmg}. \n\\---\n{#lifeSteal} si vous avez plus de {SPELLCOUNTvalue:n} en main.",
        "en": "",
        "es": "",
        "de": "",
        "pt": ""
    }
}