{
    "values": {
        "type": "SpellDefinition",
        "id": 155058,
        "merchantCosts": [],
        "premiumItem": false,
        "rarity": 0,
        "unlockableSkillIds": [],
        "upgradeRuleId": null,
        "canCrit": false,
        "isEphemeral": false,
        "tags": [],
        "details": {
            "type": "SpellDetails",
            "equipableByPlayers": false,
            "element": null,
            "specificToWeapon": null,
            "families": [
                62
            ],
            "heroSkillPointsCost": null,
            "bannedInPvp": false
        },
        "gaugeToModifyOnSpellPlay": [],
        "costs": [
            {
                "type": "ActionPointsCost",
                "value": {
                    "type": "ConstIntegerValue",
                    "referenceId": "",
                    "value": 3
                }
            }
        ],
        "castCondition": null,
        "castTarget": {
            "type": "OneCastTargetDefinition",
            "selector": {
                "type": "FilteredCharacterSelector",
                "filters": [
                    {
                        "type": "TeamFilter",
                        "isIdentical": false,
                        "reference": {
                            "type": "CasterSelector"
                        }
                    }
                ]
            }
        },
        "spellEffectData": [
            {
                "type": "SpellEffectInstantiationData",
                "spellEffect": "4a1e9c5792e3a8a40a2881ef611496c0",
                "originTarget": {
                    "type": "FirstCastTargetSelector"
                },
                "orientation": null,
                "delay": null
            }
        ],
        "precomputedData": {
            "type": "PrecomputedData",
            "dynamicValueReferences": [
                {
                    "type": "BuffedScalingDynamicValue",
                    "referenceId": "min",
                    "baseValue": {
                        "type": "ConstIntegerValue",
                        "referenceId": "",
                        "value": 15
                    },
                    "factor": {
                        "type": "ReferenceScalingFactor",
                        "reference": 11
                    },
                    "buffs": [
                        51
                    ],
                    "skillBuffs": [],
                    "from": {
                        "type": "CasterSelector"
                    },
                    "addInsteadOfMultiply": false
                },
                {
                    "type": "BuffedScalingDynamicValue",
                    "referenceId": "max",
                    "baseValue": {
                        "type": "ConstIntegerValue",
                        "referenceId": "",
                        "value": 18
                    },
                    "factor": {
                        "type": "ReferenceScalingFactor",
                        "reference": 11
                    },
                    "buffs": [
                        51
                    ],
                    "skillBuffs": [],
                    "from": {
                        "type": "CasterSelector"
                    },
                    "addInsteadOfMultiply": false
                }
            ],
            "externalDynamicValueReferences": [],
            "hasEffects": true,
            "keywordReferences": []
        }
    },
    "name": {
        "fr": "Coup de Bulbe",
        "en": "Bulb Blow",
        "es": "Golpe de Bulbo",
        "de": "Knollensto\u00df",
        "pt": "Golpe de Bulbo"
    },
    "description": {
        "fr": "Inflige {magicalPowerValue:min} \u00e0 {magicalDamage:max}.",
        "en": "Does {magicalPowerValue:min} to {magicalDamage:max}.",
        "es": "Inflige {magicalPowerValue:min} a {magicalDamage:max}.",
        "de": "Verursacht {magicalPowerValue:min} bis {magicalDamage:max}.",
        "pt": "Inflige de {magicalPowerValue:min} a {magicalDamage:max}."
    }
}