{
    "values": {
        "type": "SpellDefinition",
        "id": 156978,
        "merchantCosts": [],
        "premiumItem": false,
        "rarity": 0,
        "unlockableSkillIds": [],
        "upgradeRuleId": null,
        "canCrit": false,
        "isEphemeral": false,
        "tags": [],
        "details": {
            "type": "SpellDetails",
            "equipableByPlayers": false,
            "element": null,
            "specificToWeapon": null,
            "families": [
                75
            ],
            "heroSkillPointsCost": null,
            "bannedInPvp": false
        },
        "gaugeToModifyOnSpellPlay": [],
        "costs": [
            {
                "type": "ActionPointsCost",
                "value": {
                    "type": "ConstIntegerValue",
                    "referenceId": "",
                    "value": 3
                }
            }
        ],
        "castCondition": null,
        "castTarget": {
            "type": "OneCastTargetDefinition",
            "selector": {
                "type": "FilteredCharacterSelector",
                "filters": []
            }
        },
        "spellEffectData": [
            {
                "type": "SpellEffectInstantiationData",
                "spellEffect": "d3211b45900375d4981e7a60c9e80aed",
                "originTarget": {
                    "type": "FirstCastTargetSelector"
                },
                "orientation": null,
                "delay": null
            }
        ],
        "precomputedData": {
            "type": "PrecomputedData",
            "dynamicValueReferences": [],
            "externalDynamicValueReferences": [],
            "hasEffects": true,
            "keywordReferences": [
                {
                    "type": 22,
                    "id": 113
                }
            ]
        }
    },
    "name": {
        "fr": "Temps mort",
        "en": "Down Time",
        "es": "Tiempo Muerto",
        "de": "Auszeit",
        "pt": "Tempo Morto"
    },
    "description": {
        "fr": "Piochez un {%SPELLCOUNT} pour chaque {aura:113,plural:one} que la cible poss\u00e8de.\n\\---\nConsomme toutes ses {%KEYWORD.AURA.NAME,plural:other}.",
        "en": "Draw one {%SPELLCOUNT} for each\\_{aura:113,plural:one} that the target has.\n\\---\nConsumes all their {%KEYWORD.AURA.NAME,plural:other}.",
        "es": "Sacas un {%SPELLCOUNT} por cada {aura:113,plural:one} que tenga el objetivo.\n\\---\nConsume todas sus {%KEYWORD.AURA.NAME,plural:other}.",
        "de": "Zieht einen {%SPELLCOUNT} f\u00fcr jede {aura:113,plural:one}, die das Ziel besitzt.\n\\---\nVerbraucht alle seine {%KEYWORD.AURA.NAME,plural:other}.",
        "pt": "Compre um {%SPELLCOUNT} por cada {aura:113,plural:one} que o alvo possuir.\n\\---\nConsome todas as {%KEYWORD.AURA.NAME,plural:other}."
    }
}